totoapicontroller/TotoDelegateDecorator.py
totoapicontroller/TotoLogger.py
totoapicontroller/TotoTokenVerifier.py
totoapicontroller/__init__.py
totoapicontroller/model/ExecutionContext.py
totoapicontroller/model/TotoConfig.py
totoapicontroller/model/UserContext.py
totoapicontroller/model/ValidationResult.py
totoapicontroller/model/__init__.py
totoapicontroller/model/singleton.py
totoapicontroller-1.0.0.dist-info/METADATA
totoapicontroller-1.0.0.dist-info/WHEEL
totoapicontroller-1.0.0.dist-info/top_level.txt
totoapicontroller-1.0.0.dist-info/RECORD
